.editorconfig
.git-blame-ignore-revs
.gitattributes
.gitignore
.pre-commit-config.yaml
CONTRIBUTORS.md
LICENSE.txt
MANIFEST.in
Makefile
README.md
codecov.yml
pyproject.toml
.github/CONTRIBUTING.md
.github/ISSUE_TEMPLATE/bug_form.yaml
.github/ISSUE_TEMPLATE/bug_report.md
.github/ISSUE_TEMPLATE/config.yml
.github/ISSUE_TEMPLATE/feature_request.md
.github/workflows/build-macos.yml
.github/workflows/test.yml
.tx/config
package/entitlements.plist
package/fix_app_qt_folder_names_for_codesign.py
package/icon-symbolic.svg
package/icon.icns
package/macos-package-app.sh
package/vorta.spec
requirements.d/Brewfile
src/vorta/__init__.py
src/vorta/__main__.py
src/vorta/_version.py
src/vorta/application.py
src/vorta/autostart.py
src/vorta/config.py
src/vorta/filedialog.py
src/vorta/log.py
src/vorta/notifications.py
src/vorta/profile_export.py
src/vorta/qt_single_application.py
src/vorta/scheduler.py
src/vorta/tray_menu.py
src/vorta/updater.py
src/vorta/utils.py
src/vorta.egg-info/PKG-INFO
src/vorta.egg-info/SOURCES.txt
src/vorta.egg-info/dependency_links.txt
src/vorta.egg-info/entry_points.txt
src/vorta.egg-info/requires.txt
src/vorta.egg-info/top_level.txt
src/vorta/assets/UI/about_tab.ui
src/vorta/assets/UI/archive_tab.ui
src/vorta/assets/UI/change_passphrase.ui
src/vorta/assets/UI/diff_dialog.ui
src/vorta/assets/UI/diff_result.ui
src/vorta/assets/UI/exception_dialog.ui
src/vorta/assets/UI/exclude_dialog.ui
src/vorta/assets/UI/export_window.ui
src/vorta/assets/UI/extract_dialog.ui
src/vorta/assets/UI/import_window.ui
src/vorta/assets/UI/log_page.ui
src/vorta/assets/UI/main_window.ui
src/vorta/assets/UI/misc_tab.ui
src/vorta/assets/UI/networks_page.ui
src/vorta/assets/UI/profile_add.ui
src/vorta/assets/UI/repo_add.ui
src/vorta/assets/UI/repo_tab.ui
src/vorta/assets/UI/schedule_page.ui
src/vorta/assets/UI/schedule_tab.ui
src/vorta/assets/UI/shell_commands_page.ui
src/vorta/assets/UI/source_tab.ui
src/vorta/assets/UI/ssh_add.ui
src/vorta/assets/exclusion_presets/apps.json
src/vorta/assets/exclusion_presets/browsers.json
src/vorta/assets/exclusion_presets/dev.json
src/vorta/assets/exclusion_presets/media.json
src/vorta/assets/exclusion_presets/temp.json
