Metadata-Version: 2.4
Name: vorta
Version: 0.11.3
Summary: A GUI for Borg Backup
Author: Manuel Riel and Vorta contributors
License-Expression: GPL-3.0-only
Project-URL: Homepage, https://github.com/borgbase/vorta
Project-URL: Bug Tracker, https://github.com/borgbase/vorta/issues
Project-URL: Documentation, https://docs.borgbase.com
Project-URL: Source Code, https://github.com/borgbase/vorta
Keywords: backup,borgbackup
Classifier: Development Status :: 4 - Beta
Classifier: Environment :: MacOS X
Classifier: Environment :: X11 Applications :: Qt
Classifier: Operating System :: MacOS
Classifier: Operating System :: POSIX
Classifier: Programming Language :: Python :: 3
Classifier: Topic :: System :: Archiving :: Backup
Classifier: Topic :: System :: Systems Administration
Classifier: Topic :: Utilities
Requires-Python: >=3.8
License-File: LICENSE.txt
Requires-Dist: packaging
Requires-Dist: peewee
Requires-Dist: platformdirs<5.0.0,>=2.6.0; sys_platform != "darwin"
Requires-Dist: platformdirs<5.0.0,>=3.0.0; sys_platform == "darwin"
Requires-Dist: psutil
Requires-Dist: pyobjc-core<13; sys_platform == "darwin"
Requires-Dist: pyobjc-framework-Cocoa<13; sys_platform == "darwin"
Requires-Dist: pyobjc-framework-CoreWLAN<13; sys_platform == "darwin"
Requires-Dist: pyobjc-framework-LaunchServices<13; sys_platform == "darwin"
Requires-Dist: pyqt6
Requires-Dist: secretstorage; sys_platform != "darwin"
Provides-Extra: test
Requires-Dist: pytest; extra == "test"
Requires-Dist: pytest-qt; extra == "test"
Requires-Dist: pytest-mock; extra == "test"
Requires-Dist: pytest-cov; extra == "test"
Dynamic: license-file
